LICENSE
MANIFEST.in
README.md
package.json
setup.py
dash_extra_ui_components/BreadcrumbsDashUiComponents.py
dash_extra_ui_components/Button.py
dash_extra_ui_components/CaptchaDashUiComponents.py
dash_extra_ui_components/Carousel.py
dash_extra_ui_components/CarouselComponent.py
dash_extra_ui_components/CurrentPageReport.py
dash_extra_ui_components/DataScrollerDashUiComponents.py
dash_extra_ui_components/FirstPageLink.py
dash_extra_ui_components/Geolocator.py
dash_extra_ui_components/GeolocatorComponent.py
dash_extra_ui_components/GeolocatorDashUiComponents.py
dash_extra_ui_components/InputText.py
dash_extra_ui_components/LastPageLink.py
dash_extra_ui_components/ListBox.py
dash_extra_ui_components/ListBoxComponent.py
dash_extra_ui_components/ListBoxHeader.py
dash_extra_ui_components/ListBoxItem.py
dash_extra_ui_components/MenuBar.py
dash_extra_ui_components/MenuBarComponent.py
dash_extra_ui_components/MenubarSub.py
dash_extra_ui_components/MicrophoneDashUiComponents.py
dash_extra_ui_components/NextPageLink.py
dash_extra_ui_components/OrganizationChart.py
dash_extra_ui_components/OrganizationChartComponent.py
dash_extra_ui_components/PDFViewerComponent.py
dash_extra_ui_components/PageLinks.py
dash_extra_ui_components/PaginatorDashUiComponents.py
dash_extra_ui_components/PanelMenu.py
dash_extra_ui_components/PanelMenuComponent.py
dash_extra_ui_components/PrevPageLink.py
dash_extra_ui_components/Rating.py
dash_extra_ui_components/RatingComponent.py
dash_extra_ui_components/Steps.py
dash_extra_ui_components/StepsComponent.py
dash_extra_ui_components/TreeDashUiComponents.py
dash_extra_ui_components/TrelloComponent.py
dash_extra_ui_components/UITreeNode.py
dash_extra_ui_components/WebcamDashUiComponents.py
dash_extra_ui_components/__init__.py
dash_extra_ui_components/_imports_.py
dash_extra_ui_components/dash_extra_ui_components.min.js
dash_extra_ui_components/dash_extra_ui_components.min.js.map
dash_extra_ui_components/metadata.json
dash_extra_ui_components.egg-info/PKG-INFO
dash_extra_ui_components.egg-info/SOURCES.txt
dash_extra_ui_components.egg-info/dependency_links.txt
dash_extra_ui_components.egg-info/top_level.txt
